s_ball_anagram/__about__.py
s_ball_anagram/__init__.py
s_ball_anagram/__main__.py
s_ball_anagram/anagram.py
s_ball_anagram-0.1.1.dist-info/METADATA
s_ball_anagram-0.1.1.dist-info/WHEEL
s_ball_anagram-0.1.1.dist-info/entry_points.txt
s_ball_anagram-0.1.1.dist-info/licenses/LICENSE.txt
s_ball_anagram-0.1.1.dist-info/RECORD
