Metadata-Version: 2.4
Name: s-ball-anagram
Version: 0.1.1
Project-URL: Documentation, https://github.com/s-ball/s-ball-anagram#readme
Project-URL: Issues, https://github.com/s-ball/s-ball-anagram/issues
Project-URL: Source, https://github.com/s-ball/s-ball-anagram
Author-email: s-ball <s-ball@laposte.net>
License-Expression: MIT
License-File: LICENSE.txt
Classifier: Development Status :: 4 - Beta
Classifier: Programming Language :: Python
Classifier: Programming Language :: Python :: 3.9
Classifier: Programming Language :: Python :: 3.10
Classifier: Programming Language :: Python :: 3.11
Classifier: Programming Language :: Python :: 3.12
Classifier: Programming Language :: Python :: 3.13
Requires-Python: >=3.9
Requires-Dist: dict-fr-au-dela
